{
  "slug": "prd-dto-inheritance-standard",
  "phase": "po_close",
  "at": "2026-05-28T18:04:23Z",
  "verdict": "ready_for_human_review",
  "blockers": 0,
  "majors": 0,
  "minors": 2,
  "nits": 2,
  "acPass": 15,
  "acTotal": 15,
  "testsPassed": 119,
  "testsTotal": 119,
  "analyzeErrors": 0,
  "analyzeWarnings": 0,
  "filesReviewed": 17,
  "filesInChangeMap": 15,
  "filesOutOfScope": 2,
  "outOfScopeFiles": [
    "lib/core/http/api_base_url_resolver.dart (pre-existing dirty file, local API toggle)",
    "docs/iter-7-scope.md (planning annotation, unrelated to this PRD)"
  ],
  "manualProbesRequired": 8,
  "humanActionsRequired": [
    "Revert lib/core/http/api_base_url_resolver.dart shouldUseLocalApi = true to remoteBaseUrl.isEmpty before merging",
    "Run manual probes MP-1 through MP-8 on simulator or device"
  ],
  "followUpTechDebt": [
    "CreateMaintenanceRequestDto for _buildCreateBody (architect Decision 2)",
    "Migrate vehicles/data/dto/soat_dto.dart (deferred — requires model unification)",
    "Migrate notifications/data/dto/notification_dto.dart (deferred — requires mapper extraction)",
    "Add serialization roundtrip unit tests for migrated DTOs"
  ],
  "recommendedCommitMessage": "refactor: migrate all eligible DTOs to Pattern B (XDto extends XModel)",
  "pass": true
}
